{
    "name": "Vegetarian Beer Chili (flavorful + delicious) - Fit Foodie Finds",
    "link": "",
    "cuisine": "",
    "tags": [
        ""
    ],
    "ingredients": [
        "2 tablespoons EVOO",
        "1 large green bell pepper, diced",
        "1 large red bell pepper, diced",
        "1/2 red onion, finely diced",
        "1 tablespoon garlic, minced",
        "1 28 oz. can diced tomatoes",
        "1 4 oz. can chopped jalape\u00f1os",
        "1 6 oz. can tomato paste",
        "1 15 oz. can kidney beans, drained",
        "1 15 oz. can black beans, drained",
        "1 15 oz. can garbanzo beans, drained",
        "1 12 oz. bottle lager (light) beer",
        "1/4 cup chili seasoning",
        "1 tablespoon maple syrup",
        "1/4 teaspoon sea salt"
    ],
    "instructions": [
        "In a large pot, heat EVOO to medium/high and saut\u00e9 onion, garlic, red pepper, and green pepper.",
        "When onions are translucent, add the rest of the ingredients to the pot and bring to a boil.",
        "Turn to low and let simmer for 10 minutes and enjoy."
    ],
    "servings": "",
    "nutrition": ""
}